lapis/__init__.py
lapis/__main__.py
lapis/errata.py
lapis/openapi/model.py
lapis/render/__init__.py
lapis/render/black.py
lapis/render/elems/__init__.py
lapis/render/elems/attribute.py
lapis/render/elems/attribute_annotation.py
lapis/render/elems/client_class.py
lapis/render/elems/client_module.py
lapis/render/elems/module.py
lapis/render/elems/modules.py
lapis/render/elems/operation_function.py
lapis/render/elems/param_model_class.py
lapis/render/elems/pyproject.py
lapis/render/elems/refs.py
lapis/render/elems/request_body.py
lapis/render/elems/response_body.py
lapis/render/elems/schema_class.py
lapis/render/elems/schema_module.py
lapis/render/module_path.py
lapis/render/render.py
lapis/render/templates/__init__.py
lapis/render/templates/client_class.py.jinja2
lapis/render/templates/module.py.jinja2
lapis/render/templates/pyproject.toml
lapis/render/templates/schema_class.py.jinja2
lapis/render/templates/schema_class_enum.py.jinja2
lapis/render/templates/schema_class_object.py.jinja2
lapis/render/templates/type_hint.py.jinja2
lapis/render/type_ref.py
lapis_gen-0.3.1.dist-info/entry_points.txt
lapis_gen-0.3.1.dist-info/WHEEL
lapis_gen-0.3.1.dist-info/METADATA
lapis_gen-0.3.1.dist-info/RECORD
