Metadata-Version: 2.1
Name: lapis-gen
Version: 0.3.1
Summary: Python API client generator
Home-page: https://github.com/lapis-project/lapis
License: AGPL-3.0
Author: Raphael Krupinski
Author-email: rafalkrupinski@users.noreply.github.com
Requires-Python: >=3.9,<4.0
Classifier: License :: OSI Approved :: GNU Affero General Public License v3
Classifier: Programming Language :: Python :: 3
Classifier: Programming Language :: Python :: 3.9
Classifier: Programming Language :: Python :: 3.10
Requires-Dist: Jinja2 (>=3.1.2,<4.0.0)
Requires-Dist: PyYAML (>=6.0,<7.0)
Requires-Dist: black (>=22.8.0,<23.0.0)
Requires-Dist: inflection (>=0.5.1,<0.6.0)
Requires-Dist: jsonpatch (>=1.32,<2.0)
Requires-Dist: lapis-client-base (>=0.2.2,<0.3.0)
Requires-Dist: pydantic[email] (>=1.9.2,<2.0.0)
Requires-Dist: python-mimeparse (>=1.6.0,<2.0.0)
Requires-Dist: tomlkit (>=0.11.4,<0.12.0)
Requires-Dist: typer (>=0.6.1,<0.7.0)
Project-URL: Repository, https://github.com/lapis-project/lapis
